demostat/__init__.py
demostat/admin.py
demostat/apps.py
demostat/models.py
demostat/tests.py
demostat/urls.py
demostat/utils.py
demostat/views.py
demostat/migrations/0001_initial.py
demostat/migrations/__init__.py
demostat/static/demostat/bootstrap/css/bootstrap.min.css
demostat/static/demostat/bootstrap/js/bootstrap.min.js
demostat/static/demostat/demostat/css/style.css
demostat/static/demostat/demostat/js/script.js
demostat/static/demostat/jquery/js/jquery.slim.min.js
demostat/static/demostat/leaflet/leaflet-src.esm.js
demostat/static/demostat/leaflet/leaflet-src.esm.js.map
demostat/static/demostat/leaflet/leaflet-src.js
demostat/static/demostat/leaflet/leaflet-src.js.map
demostat/static/demostat/leaflet/leaflet.css
demostat/static/demostat/leaflet/leaflet.js
demostat/static/demostat/leaflet/leaflet.js.map
demostat/static/demostat/leaflet/images/layers-2x.png
demostat/static/demostat/leaflet/images/layers.png
demostat/static/demostat/leaflet/images/marker-icon-2x.png
demostat/static/demostat/leaflet/images/marker-icon.png
demostat/static/demostat/leaflet/images/marker-shadow.png
demostat/templates/demostat/about.html
demostat/templates/demostat/base.html
demostat/templates/demostat/demo_detail.html
demostat/templates/demostat/demos_list.html
demostat/templates/demostat/demos_month_list.html
demostat/templates/demostat/demos_year_list.html
demostat/templates/demostat/index.html
demostat/templates/demostat/organisation_detail.html
demostat/templates/demostat/tag_detail.html
demostat/templates/demostat/components/demo_card.html
demostat/templates/demostat/components/demo_card_list.html
demostat/templates/demostat/components/demo_tag_filter_bar.html
demostat/templates/demostat/components/demos_month_pagination_bar.html
demostat/templates/demostat/components/demos_year_pagination_bar.html
demostat/templatetags/__init__.py
demostat/templatetags/demostat_tag_filter.py
demostat-0.2.3.dist-info/LICENSE
demostat-0.2.3.dist-info/METADATA
demostat-0.2.3.dist-info/WHEEL
demostat-0.2.3.dist-info/top_level.txt
demostat-0.2.3.dist-info/RECORD
