Metadata-Version: 2.1
Name: demostat
Version: 0.2.3
Summary: Status page for scheduled political demonstrations
Home-page: https://demostat.de/
Author: Clemens Riese
Author-email: hallo@clerie.de
License: UNKNOWN
Platform: UNKNOWN
Classifier: Environment :: Web Environment
Classifier: Framework :: Django
Classifier: Framework :: Django :: 2.1
Classifier: Intended Audience :: Developers
Classifier: Operating System :: OS Independent
Classifier: Programming Language :: Python
Classifier: Programming Language :: Python :: 3.5
Classifier: Programming Language :: Python :: 3 :: Only
Classifier: Topic :: Internet :: WWW/HTTP
Classifier: Topic :: Internet :: WWW/HTTP :: Dynamic Content
Requires-Python: >=3.5
Requires-Dist: Django (>=2.1)
